LICENSE
MANIFEST.in
README.md
requirements.txt
setup.cfg
setup.py
pyculiar.egg-info/PKG-INFO
pyculiar.egg-info/SOURCES.txt
pyculiar.egg-info/dependency_links.txt
pyculiar.egg-info/requires.txt
pyculiar.egg-info/top_level.txt
pyculiarity/__init__.py
pyculiarity/date_utils.py
pyculiarity/detect_anoms.py
pyculiarity/detect_ts.py
pyculiarity/stl.py
tests/midnight_test_data.csv
tests/raw_data.csv
tests/test_edge.py
tests/test_na.py
tests/test_ts.py