Metadata-Version: 1.1
Name: pyculiar
Version: 0.0.5
Summary: A pure python port of Twitter's AnomalyDetection R Package.
Home-page: https://github.com/wdm0006/pyculiarity
Author: Will McGinnis & Nicolas Steven Miller
Author-email: will@predikto.com
License: GPL
Download-URL: https://github.com/wdm0006/pyculiarity/tarball/0.0.5
Keywords: data anomaly detection pandas timeseries
Platform: UNKNOWN
Classifier: Development Status :: 3 - Alpha
Classifier: Intended Audience :: Developers
Classifier: Topic :: Scientific/Engineering
Classifier: License :: OSI Approved :: GNU General Public License v3 (GPLv3)
Classifier: Programming Language :: Python :: 2.7
Classifier: Programming Language :: Python :: 2
Classifier: Programming Language :: Python :: 3
